KratosMultiphysics/RANSApplication/__init__.py
KratosMultiphysics/RANSApplication/apply_wall_function_process.py
KratosMultiphysics/RANSApplication/coupled_rans_solver.py
KratosMultiphysics/RANSApplication/cpp_process_factory.py
KratosMultiphysics/RANSApplication/rans_analysis.py
KratosMultiphysics/RANSApplication/formulations/__init__.py
KratosMultiphysics/RANSApplication/formulations/rans_formulation.py
KratosMultiphysics/RANSApplication/formulations/utilities.py
KratosMultiphysics/RANSApplication/formulations/fractional_step/fractional_step_k_epsilon_rans_formulation.py
KratosMultiphysics/RANSApplication/formulations/fractional_step/fractional_step_k_omega_rans_formulation.py
KratosMultiphysics/RANSApplication/formulations/fractional_step/fractional_step_k_omega_sst_rans_formulation.py
KratosMultiphysics/RANSApplication/formulations/fractional_step/fractional_step_velocity_pressure_rans_formulation.py
KratosMultiphysics/RANSApplication/formulations/incompressible_potential_flow/__init__.py
KratosMultiphysics/RANSApplication/formulations/monolithic_vms/monolithic_k_epsilon_rans_formulation.py
KratosMultiphysics/RANSApplication/formulations/monolithic_vms/monolithic_k_omega_rans_formulation.py
KratosMultiphysics/RANSApplication/formulations/monolithic_vms/monolithic_k_omega_sst_rans_formulation.py
KratosMultiphysics/RANSApplication/formulations/monolithic_vms/monolithic_velocity_pressure_rans_formulation.py
KratosMultiphysics/RANSApplication/formulations/turbulence_models/k_epsilon_rans_formulation.py
KratosMultiphysics/RANSApplication/formulations/turbulence_models/k_omega_rans_formulation.py
KratosMultiphysics/RANSApplication/formulations/turbulence_models/k_omega_sst_rans_formulation.py
KratosMultiphysics/RANSApplication/formulations/turbulence_models/scalar_turbulence_model_rans_formulation.py
KratosMultiphysics/RANSApplication/formulations/turbulence_models/two_equation_turbulence_model_rans_formulation.py
KratosMultiphysics/.libs/KratosRANSApplication.pyd
kratosransapplication-10.4.0.dist-info/METADATA
kratosransapplication-10.4.0.dist-info/WHEEL
kratosransapplication-10.4.0.dist-info/RECORD
